cocotbext/vidio/__init__.py
cocotbext/vidio/colorconv.py
cocotbext/vidio/constants.py
cocotbext/vidio/csc.py
cocotbext/vidio/tpg.py
cocotbext/vidio/utils.py
cocotbext/vidio/version.py
cocotbext/vidio/vidio.py
cocotbext_vidio-0.1.1.dist-info/LICENSE
cocotbext_vidio-0.1.1.dist-info/METADATA
cocotbext_vidio-0.1.1.dist-info/WHEEL
cocotbext_vidio-0.1.1.dist-info/top_level.txt
cocotbext_vidio-0.1.1.dist-info/RECORD
