Metadata-Version: 2.1
Name: cocotbext-vidio
Version: 0.1.1
Summary: AXIS video subsystem for cocotb
Home-page: https://github.com/nitheeshkm/cocotbext-vidio
Download-URL: https://github.com/nitheeshkm/cocotbext-vidio/tarball/main
Author: Nitheesh Manjunath
Author-email: nitheesh2013@gmail.com
License: MIT
Project-URL: Bug Tracker, https://github.com/nitheeshkm/cocotbext-vidio/issues
Project-URL: Source Code, https://github.com/nitheeshkm/cocotbext-vidio
Keywords: axi,cocotb
Platform: any
Classifier: Development Status :: 1 - Planning
Classifier: Framework :: cocotb
Classifier: License :: OSI Approved :: MIT License
Classifier: Operating System :: OS Independent
Classifier: Programming Language :: Python :: 3
Classifier: Topic :: Scientific/Engineering :: Electronic Design Automation (EDA)
Requires-Python: >=3.6
License-File: LICENSE
Requires-Dist: cocotb >=1.6.0
Requires-Dist: cocotb-bus
Requires-Dist: cocotbext-axi
Requires-Dist: numpy
Provides-Extra: test
Requires-Dist: pytest ; extra == 'test'
Requires-Dist: cocotb-test ; extra == 'test'
